masumi_crewai/__init__.py
masumi_crewai/config.py
masumi_crewai/payment.py
masumi_crewai/purchase.py
masumi_crewai/registry.py
masumi_crewai/utils.py
masumi_crewai-0.1.24.dist-info/METADATA
masumi_crewai-0.1.24.dist-info/WHEEL
masumi_crewai-0.1.24.dist-info/top_level.txt
masumi_crewai-0.1.24.dist-info/RECORD
